{
  "requestsFinished": 0,
  "requestsFailed": 0,
  "requestsRetries": 0,
  "requestsFailedPerMinute": 0,
  "requestsFinishedPerMinute": 0,
  "requestMinDurationMillis": null,
  "requestMaxDurationMillis": 0,
  "requestTotalFailedDurationMillis": 0,
  "requestTotalFinishedDurationMillis": 0,
  "crawlerStartedAt": "2025-02-17T02:15:26.711Z",
  "crawlerFinishedAt": "2025-02-17T02:15:27.053Z",
  "statsPersistedAt": "2025-02-17T02:15:27.053Z",
  "crawlerRuntimeMillis": 366,
  "crawlerLastStartTimestamp": 1739758526687,
  "requestRetryHistogram": [],
  "statsId": 3,
  "requestAvgFailedDurationMillis": null,
  "requestAvgFinishedDurationMillis": null,
  "requestTotalDurationMillis": 0,
  "requestsTotal": 0,
  "requestsWithStatusCode": {},
  "errors": {},
  "retryErrors": {}
}